pydantic_asyncapi/__about__.py
pydantic_asyncapi/__init__.py
pydantic_asyncapi/common.py
pydantic_asyncapi/py.typed
pydantic_asyncapi/v2.py
pydantic_asyncapi/v3.py
pydantic_asyncapi/bindings/__init__.py
pydantic_asyncapi/bindings/amqp.py
pydantic_asyncapi/bindings/kafka.py
pydantic_asyncapi/bindings/nats.py
pydantic_asyncapi/bindings/sqs.py
pydantic_asyncapi-0.3.0.dist-info/METADATA
pydantic_asyncapi-0.3.0.dist-info/WHEEL
pydantic_asyncapi-0.3.0.dist-info/licenses/LICENSE
pydantic_asyncapi-0.3.0.dist-info/RECORD
