Metadata-Version: 2.4
Name: pydantic-asyncapi
Version: 0.3.0
Summary: Pydantic models of AsyncAPI schema
Project-URL: Documentation, https://github.com/asynq-io/pydantic-asyncapi#readme
Project-URL: Issues, https://github.com/asynq-io/pydantic-asyncapi/issues
Project-URL: Source, https://github.com/asynq-io/pydantic-asyncapi
Author-email: RaRhAeu <rarha_eu@protonmail.com>
License-Expression: Apache-2.0
License-File: LICENSE
Keywords: asyncapi,pydantic,schema
Classifier: Development Status :: 4 - Beta
Classifier: Framework :: Pydantic :: 2
Classifier: Intended Audience :: Developers
Classifier: Natural Language :: English
Classifier: Operating System :: OS Independent
Classifier: Programming Language :: Python
Classifier: Programming Language :: Python :: 3.9
Classifier: Programming Language :: Python :: 3.10
Classifier: Programming Language :: Python :: 3.11
Classifier: Programming Language :: Python :: 3.12
Classifier: Programming Language :: Python :: Implementation :: CPython
Classifier: Programming Language :: Python :: Implementation :: PyPy
Classifier: Topic :: Software Development :: Libraries
Requires-Python: >=3.9
Requires-Dist: pydantic<3.0.0,>=2.0.2
